setup.py
testo/__init__.py
testo.egg-info/PKG-INFO
testo.egg-info/SOURCES.txt
testo.egg-info/dependency_links.txt
testo.egg-info/entry_points.txt
testo.egg-info/not-zip-safe
testo.egg-info/top_level.txt