Metadata-Version: 1.0
Name: testo
Version: 0.0.3
Summary: CI framework
Home-page: https://github.com/log0div0/testo
Author: Sergey Lvov
Author-email: log0div0@gmail.com
License: MIT
Platform: UNKNOWN
